Metadata-Version: 2.4
Name: jupyter-agent
Version: 2025.7.105
Summary: 调用LLM实现Jupyter代码的自动生成、执行、调试等功能
Author: viewstar000
License: MIT
Project-URL: Homepage, https://github.com/viewstar000/jupyter-agent
Classifier: Programming Language :: Python :: 3
Classifier: Operating System :: OS Independent
Requires-Python: >=3.12
License-File: LICENSE
Requires-Dist: bottle
Requires-Dist: ipynbname
Requires-Dist: ipython
Requires-Dist: jinja2
Requires-Dist: nbclient
Requires-Dist: nbformat
Requires-Dist: openai
Requires-Dist: pydantic
Requires-Dist: pyyaml
Requires-Dist: traitlets
Dynamic: license-file
